evr/__init__.py
evr/__main__.py
evr/api.py
evr/cli.py
evr/model.py
evr/py.typed
evr/venues.tsv
evr/version.py
evr-0.0.1.dist-info/METADATA
evr-0.0.1.dist-info/WHEEL
evr-0.0.1.dist-info/entry_points.txt
evr-0.0.1.dist-info/top_level.txt
evr-0.0.1.dist-info/RECORD
