Metadata-Version: 2.1
Name: evr
Version: 0.0.1
Summary: An open, community-driven venue of conference and event venues
Author-email: Charles Tapley Hoyt <cthoyt@gmail.com>
Maintainer-email: Charles Tapley Hoyt <cthoyt@gmail.com>
License: MIT License
Project-URL: Bug Tracker, https://github.com/cthoyt/evr/issues
Project-URL: Homepage, https://github.com/cthoyt/evr
Project-URL: Repository, https://github.com/cthoyt/evr.git
Project-URL: Documentation, https://evr.readthedocs.io
Project-URL: Funding, https://github.com/sponsors/cthoyt
Keywords: snekpack,cookiecutter
Classifier: Development Status :: 1 - Planning
Classifier: Environment :: Console
Classifier: Intended Audience :: Developers
Classifier: License :: OSI Approved :: MIT License
Classifier: Operating System :: OS Independent
Classifier: Framework :: Pytest
Classifier: Framework :: tox
Classifier: Framework :: Sphinx
Classifier: Natural Language :: English
Classifier: Programming Language :: Python
Classifier: Programming Language :: Python :: 3.10
Classifier: Programming Language :: Python :: 3.11
Classifier: Programming Language :: Python :: 3.12
Classifier: Programming Language :: Python :: 3.13
Classifier: Programming Language :: Python :: 3 :: Only
Classifier: Typing :: Typed
Requires-Python: >=3.10
Requires-Dist: pydantic
Requires-Dist: pycountry
Requires-Dist: pydantic_extra_types
Requires-Dist: semantic-pydantic
Requires-Dist: tqdm
Provides-Extra: tests
Requires-Dist: pytest; extra == "tests"
Requires-Dist: coverage; extra == "tests"
Provides-Extra: docs
Requires-Dist: sphinx>=8; extra == "docs"
Requires-Dist: sphinx-rtd-theme>=3.0; extra == "docs"
Requires-Dist: sphinx-click; extra == "docs"
Requires-Dist: sphinx_automodapi; extra == "docs"
Provides-Extra: ontology-export
Requires-Dist: pyobo; extra == "ontology-export"
Requires-Dist: bioontologies; extra == "ontology-export"
